RTL/tea_accelerator.sv
// Author: Mitchell Sharum
// Date Created: 3/2/2025
// Purpose: The TEA accekerator itself, the topmost level due to the limited size of the harware

module tea_accelerator(
    
    input logic i_clk,                      // synchronizing clock
    input logic i_rst,                      // synchronous active-high reset

    input logic [127:0] i_key,              // 128-bit encryption key
    
    input logic i_axis_valid_s,             // asserted by upstream circuit when it is ready to transmit the input block
    output logic o_axis_ready_s,            // asserted to request input block fromt he upstream circuit
    input logic [63:0] i_axis_data_s,       // the input block to be encrypted  

    output logic o_axis_valid_m,            // asserted to inform downstream circuit that data is ready
    input logic i_axis_ready_m,             // asserted by downstream circuit to rquest encrypted data
    output logic [63:0] o_axis_data_m       // the encrypted output
);

    // register declarations
    logic [1:0] state = 0, next_state = 0;
    logic [4:0] round_counter = 0; 
    logic [31:0] v0, v1, v0_next, v1_next;
    logic [31:0] k0, k1, k2, k3;
    logic [31:0] sum = 0;
    logic [31:0] new_sum = 0;
    logic [63:0] output_data = 0;

    // state enumeration
    localparam IDLE = 2'b00;
    localparam LOADING = 2'b01;
    localparam PROCESSING = 2'b10;
    localparam DONE = 2'b11;

    // delta constant apparently adds non-linearity
    localparam DELTA = 32'h9E3779B9;
    
    // combinatorial block for state transitions
    always @(*) begin

        // assign the updated sum to a new_sum variable
        new_sum = sum + DELTA;

        // always be calculating the next values of the v0 and v1 registers
        v0_next = v0 + (((v1 << 4) + k0) ^ (v1 + new_sum) ^ ((v1 >> 5) + k1));
        v1_next = v1 + (((v0 << 4) + k2) ^ (v0 + new_sum) ^ ((v0 >> 5) + k3));

        case (state)
            
            // when module ready to accept a data word and the upstream module is ready to provide, then move into LOADING state 
            IDLE: 
                if (i_axis_valid_s && o_axis_ready_s) begin
                    next_state = LOADING;
                end

            // load the inoput data into corresponding registers
            LOADING:
                next_state = PROCESSING;
            
            // process 32 rounds before output
            PROCESSING:
                if (round_counter >= 31) begin
                    next_state = DONE;
                end
            
            // if the downstream module is ready to receive, output encrypted data and return to IDLE       
            DONE:
                if (o_axis_valid_m && i_axis_ready_m) begin
                    next_state = IDLE;
                end
            
            // default case, remain in the same state
            default: 
                next_state = state;
        endcase
    end

    // sequential block for computing rounds
    always @(posedge i_clk) begin

        // reset handling
        if (i_rst) begin
            
            // reset state and outputs
            state <= IDLE;
            sum <= 0;
            round_counter <= 0;
            o_axis_ready_s <= 1;
            o_axis_valid_m <= 0;
            output_data <= 0;
            
            // zero operator registers
            v0 <= 0;
            v1 <= 0;
            k0 <= 0;
            k1 <= 0;
            k2 <= 0;
            k3 <= 0;

        // transition to the next state
        end else begin
            state <= next_state;

            // state case handling
            case (state)
                
                // IDLE handling
                IDLE: begin
                
                    // reset the data, sum, counter, and output registers for next data block
                    sum <= 0;
                    round_counter <= 0;
                    o_axis_valid_m <= 0;
                    output_data <= 0;
                    
                    // zero operator registers
                    v0 <= 0;
                    v1 <= 0;
                    k0 <= 0;
                    k1 <= 0;
                    k2 <= 0;
                    k3 <= 0;

                    // assert that we are ready for another input block
                    o_axis_ready_s <= 1'b1;
                end
                
                // LOADING handling
                LOADING: begin
                    
                    // load the key and input data into registers for operating rounds
                    v0 <= i_axis_data_s[63:32];
                    v1 <= i_axis_data_s[31:0];
                    k0 <= i_key[127:96];
                    k1 <= i_key[95:64];
                    k2 <= i_key[63:32];
                    k3 <= i_key[31:0];

                    // assert we are no longer ready to receive
                    o_axis_ready_s <= 1'b0;
                end 
                
                // PROCESSING handling
                PROCESSING: begin

                    // increent the sum by DELTA
                    sum <= sum + DELTA;

                    // process the current round
                    v0 <= v0_next;
                    v1 <= v1_next;

                    // increment the round counter by 1
                    round_counter <= round_counter + 1;
                end
                
                // DONE handling
                DONE: begin
                
                    // output assignment - concatenate the v0 and v1
                    output_data <= {v0,v1};

                    // tell downstream module we are ready to transmit if we are done and receive the downstream ready signal
                    if (o_axis_valid_m && i_axis_ready_m) begin
                        o_axis_valid_m <= 1'b0;

                    // if we have gitten the ready signal from downstream module, then we wait
                    end else if (!o_axis_valid_m) begin
                        o_axis_valid_m <= 1'b1;
                    end
                
                end
            endcase
        end
    end

    // final output assignment
    assign o_axis_data_m = output_data;

endmodule

Simulations/tb_tea_accelerator.sv
// Author: Mitchell Sharum
// Date Created: 3/18/2025
// Purpose: Early simulations of TEA accelrator to make sure that we are getting outputs and proper dataflow for simple cases
// will later integrate the golden model

module tb_tea_accelerator;

    // signal declarations - testbench module interface to the DUT
    logic i_clk = 0;                      
    logic i_rst;             
    logic [127:0] i_key;
    logic i_axis_valid_s;             
    logic o_axis_ready_s;           
    logic [63:0] i_axis_data_s;       
    logic o_axis_valid_m;           
    logic i_axis_ready_m;            
    logic [63:0] o_axis_data_m; 

    // DUT instantiation
    tea_accelerator dut(
        .i_clk(i_clk), 
        .i_rst(i_rst),
        .i_key(i_key),
        .i_axis_valid_s(i_axis_valid_s),
        .o_axis_ready_s(o_axis_ready_s),
        .i_axis_data_s(i_axis_data_s), 
        .o_axis_valid_m(o_axis_valid_m), 
        .i_axis_ready_m(i_axis_ready_m), 
        .o_axis_data_m(o_axis_data_m));
    
    // clock generation
    initial begin
        forever begin
            i_clk <= ~i_clk;
            #5;
        end
    end
    
    // test stimulus
    initial begin

        // dump the wavedate into a .vcd
        $dumpfile("sim_tea_accelerator.vcd");
        $dumpvars(0, tb_tea_accelerator);

        // signal initialization
        i_clk = 0;
        i_rst = 0;
        i_key = 0;
        i_axis_ready_m = 0;
        i_axis_valid_s = 0;
        i_axis_data_s = 0;
        #5;

        // test vectors
        i_rst = 1;
        #5;

        // deassert reset and supply vector
        i_rst = 0;
        i_axis_ready_m = 1;
        i_axis_valid_s = 1;
        i_key = 128'h0;
        i_axis_data_s = 64'h0;
        #5;

        // leave sim runnig until the ouput waveform can be viewed
        #2500;

        // end the simulation
        $finish;

    end
endmodule

Scripts/sim_tea_accelerator.vcd
$date
	Tue Mar 18 20:15:56 2025
$end
$version
	Icarus Verilog
$end
$timescale
	1s
$end
$scope module tb_tea_accelerator $end
$var wire 1 ! o_axis_valid_m $end
$var wire 1 " o_axis_ready_s $end
$var wire 64 # o_axis_data_m [63:0] $end
$var reg 64 $ i_axis_data_s [63:0] $end
$var reg 1 % i_axis_ready_m $end
$var reg 1 & i_axis_valid_s $end
$var reg 1 ' i_clk $end
$var reg 128 ( i_key [127:0] $end
$var reg 1 ) i_rst $end
$scope module dut $end
$var wire 64 * i_axis_data_s [63:0] $end
$var wire 1 % i_axis_ready_m $end
$var wire 1 & i_axis_valid_s $end
$var wire 1 ' i_clk $end
$var wire 128 + i_key [127:0] $end
$var wire 1 ) i_rst $end
$var wire 64 , o_axis_data_m [63:0] $end
$var parameter 32 - DELTA $end
$var parameter 2 . DONE $end
$var parameter 2 / IDLE $end
$var parameter 2 0 LOADING $end
$var parameter 2 1 PROCESSING $end
$var reg 32 2 k0 [31:0] $end
$var reg 32 3 k1 [31:0] $end
$var reg 32 4 k2 [31:0] $end
$var reg 32 5 k3 [31:0] $end
$var reg 32 6 new_sum [31:0] $end
$var reg 2 7 next_state [1:0] $end
$var reg 1 " o_axis_ready_s $end
$var reg 1 ! o_axis_valid_m $end
$var reg 64 8 output_data [63:0] $end
$var reg 5 9 round_counter [4:0] $end
$var reg 2 : state [1:0] $end
$var reg 32 ; sum [31:0] $end
$var reg 32 < v0 [31:0] $end
$var reg 32 = v0_next [31:0] $end
$var reg 32 > v1 [31:0] $end
$var reg 32 ? v1_next [31:0] $end
$upscope $end
$upscope $end
$enddefinitions $end
$comment Show the parameter values. $end
$dumpall
b10 1
b1 0
b0 /
b11 .
b10011110001101110111100110111001 -
$end
#0
$dumpvars
b10011110001101110111100110111001 ?
b0 >
b10011110001101110111100110111001 =
b0 <
b0 ;
b0 :
b0 9
b0 8
b0 7
b10011110001101110111100110111001 6
b0 5
b0 4
b0 3
b0 2
b0 ,
b0 +
b0 *
0)
b0 (
1'
0&
0%
b0 $
b0 #
1"
0!
$end
#5
0'
1)
#10
b1 :
1'
b10 7
1&
1%
0)
#15
0'
#20
0"
b10 :
1'
#25
0'
#30
b11011011010101111100011100101111 ?
b11011011010101111100011100101111 =
b111100011011101111001101110010 6
b1 9
b10011110001101110111100110111001 >
b10011110001101110111100110111001 <
b10011110001101110111100110111001 ;
1'
#35
0'
#40
b11100001101100001011111111000010 ?
b11100001101100001011111111000010 =
b11011010101001100110110100101011 6
b10 9
b11011011010101111100011100101111 >
b11011011010101111100011100101111 <
b111100011011101111001101110010 ;
1'
#45
0'
#50
b101000001110011001111100111010 ?
b101000001110011001111100111010 =
b1111000110111011110011011100100 6
b11 9
b11100001101100001011111111000010 >
b11100001101100001011111111000010 <
b11011010101001100110110100101011 ;
1'
#55
0'
#60
b11100101110100000101111111001000 ?
b11100101110100000101111111001000 =
b10111000101010110000010011101 6
b100 9
b101000001110011001111100111010 >
b101000001110011001111100111010 <
b1111000110111011110011011100100 ;
1'
#65
0'
#70
b10100111000001101010010000101000 ?
b10100111000001101010010000101000 =
b10110101010011001101101001010110 6
b101 9
b11100101110100000101111111001000 >
b11100101110100000101111111001000 <
b10111000101010110000010011101 ;
1'
#75
0'
#80
b110110110111110011001110111110 ?
b110110110111110011001110111110 =
b1010011100001000101010000001111 6
b110 9
b10100111000001101010010000101000 >
b10100111000001101010010000101000 <
b10110101010011001101101001010110 ;
1'
#85
0'
#90
b1111011101111011111011110111001 ?
b1111011101111011111011110111001 =
b11110001101110111100110111001000 6
b111 9
b110110110111110011001110111110 >
b110110110111110011001110111110 <
b1010011100001000101010000001111 ;
1'
#95
0'
#100
b101111011100011010001011010000 ?
b101111011100011010001011010000 =
b10001111111100110100011110000001 6
b1000 9
b1111011101111011111011110111001 >
b1111011101111011111011110111001 <
b11110001101110111100110111001000 ;
1'
#105
0'
#110
b11011011011011110110011011101100 ?
b11011011011011110110011011101100 =
b101110001010101100000100111010 6
b1001 9
b101111011100011010001011010000 >
b101111011100011010001011010000 <
b10001111111100110100011110000001 ;
1'
#115
0'
#120
b11110011011011000001101100010100 ?
b11110011011011000001101100010100 =
b11001100011000100011101011110011 6
b1010 9
b11011011011011110110011011101100 >
b11011011011011110110011011101100 <
b101110001010101100000100111010 ;
1'
#125
0'
#130
b1100010110010110011100101101100 ?
b1100010110010110011100101101100 =
b1101010100110011011010010101100 6
b1011 9
b11110011011011000001101100010100 >
b11110011011011000001101100010100 <
b11001100011000100011101011110011 ;
1'
#135
0'
#140
b10100111000001001110001001000110 ?
b10100111000001001110001001000110 =
b1000110100010010111001100101 6
b1100 9
b1100010110010110011100101101100 >
b1100010110010110011100101101100 <
b1101010100110011011010010101100 ;
1'
#145
0'
#150
b11100010100000000110101101011100 ?
b11100010100000000110101101011100 =
b10100111000010001010100000011110 6
b1101 9
b10100111000001001110001001000110 >
b10100111000001001110001001000110 <
b1000110100010010111001100101 ;
1'
#155
0'
#160
b11101011010100101010011100000101 ?
b11101011010100101010011100000101 =
b1000101010000000010000111010111 6
b1110 9
b11100010100000000110101101011100 >
b11100010100000000110101101011100 <
b10100111000010001010100000011110 ;
1'
#165
0'
#170
b1101000000011010100111100000010 ?
b1101000000011010100111100000010 =
b11100011011101111001101110010000 6
b1111 9
b11101011010100101010011100000101 >
b11101011010100101010011100000101 <
b1000101010000000010000111010111 ;
1'
#175
0'
#180
b11010010001101100100110100010101 ?
b11010010001101100100110100010101 =
b10000001101011110001010101001001 6
b10000 9
b1101000000011010100111100000010 >
b1101000000011010100111100000010 <
b11100011011101111001101110010000 ;
1'
#185
0'
#190
b10101010001000000000110001000100 ?
b10101010001000000000110001000100 =
b11111111001101000111100000010 6
b10001 9
b11010010001101100100110100010101 >
b11010010001101100100110100010101 <
b10000001101011110001010101001001 ;
1'
#195
0'
#200
b1111001100011111101110100100001 ?
b1111001100011111101110100100001 =
b10111110000111100000100010111011 6
b10010 9
b10101010001000000000110001000100 >
b10101010001000000000110001000100 <
b11111111001101000111100000010 ;
1'
#205
0'
#210
b11001000011001001101000010001101 ?
b11001000011001001101000010001101 =
b1011100010101011000001001110100 6
b10011 9
b1111001100011111101110100100001 >
b1111001100011111101110100100001 <
b10111110000111100000100010111011 ;
1'
#215
0'
#220
b1011011001001011001101111011 ?
b1011011001001011001101111011 =
b11111010100011001111110000101101 6
b10100 9
b11001000011001001101000010001101 >
b11001000011001001101000010001101 <
b1011100010101011000001001110100 ;
1'
#225
0'
#230
b11101100111011110111011000101 ?
b11101100111011110111011000101 =
b10011000110001000111010111100110 6
b10101 9
b1011011001001011001101111011 >
b1011011001001011001101111011 <
b11111010100011001111110000101101 ;
1'
#235
0'
#240
b10101011010010011100110000000111 ?
b10101011010010011100110000000111 =
b110110111110111110111110011111 6
b10110 9
b11101100111011110111011000101 >
b11101100111011110111011000101 <
b10011000110001000111010111100110 ;
1'
#245
0'
#250
b11011101000001011000011101010110 ?
b11011101000001011000011101010110 =
b11010101001100110110100101011000 6
b10111 9
b10101011010010011100110000000111 >
b10101011010010011100110000000111 <
b110110111110111110111110011111 ;
1'
#255
0'
#260
b1100011110001011011101010010011 ?
b1100011110001011011101010010011 =
b1110011011010101110001100010001 6
b11000 9
b11011101000001011000011101010110 >
b11011101000001011000011101010110 <
b11010101001100110110100101011000 ;
1'
#265
0'
#270
b10101101111100110100111001001100 ?
b10101101111100110100111001001100 =
b10001101000100101110011001010 6
b11001 9
b1100011110001011011101010010011 >
b1100011110001011011101010010011 <
b1110011011010101110001100010001 ;
1'
#275
0'
#280
b110101100010011010100011001001 ?
b110101100010011010100011001001 =
b10101111110110011101011010000011 6
b11010 9
b10101101111100110100111001001100 >
b10101101111100110100111001001100 <
b10001101000100101110011001010 ;
1'
#285
0'
#290
b10000001101011110000110011100 ?
b10000001101011110000110011100 =
b1001110000100010101000000111100 6
b11011 9
b110101100010011010100011001001 >
b110101100010011010100011001001 <
b10101111110110011101011010000011 ;
1'
#295
0'
#300
b1111110101101111111011111001 ?
b1111110101101111111011111001 =
b11101100010010001100100111110101 6
b11100 9
b10000001101011110000110011100 >
b10000001101011110000110011100 <
b1001110000100010101000000111100 ;
1'
#305
0'
#310
b1110111000111010001100110111001 ?
b1110111000111010001100110111001 =
b10001010100000000100001110101110 6
b11101 9
b1111110101101111111011111001 >
b1111110101101111111011111001 <
b11101100010010001100100111110101 ;
1'
#315
0'
#320
b1100100110110101011111000110110 ?
b1100100110110101011111000110110 =
b101000101101111011110101100111 6
b11110 9
b1110111000111010001100110111001 >
b1110111000111010001100110111001 <
b10001010100000000100001110101110 ;
1'
#325
0'
#330
b11 7
b11001010000111111000000111111101 ?
b11001010000111111000000111111101 =
b11000110111011110011011100100000 6
b11111 9
b1100100110110101011111000110110 >
b1100100110110101011111000110110 <
b101000101101111011110101100111 ;
1'
#335
0'
#340
b1010011000011100101001100000110 ?
b1010011000011100101001100000110 =
b1100101001001101011000011011001 6
b0 9
b11001010000111111000000111111101 >
b11001010000111111000000111111101 <
b11000110111011110011011100100000 ;
b11 :
1'
#345
0'
#350
b0 7
1!
b1100101000011111100000011111110111001010000111111000000111111101 #
b1100101000011111100000011111110111001010000111111000000111111101 ,
b1100101000011111100000011111110111001010000111111000000111111101 8
1'
#355
0'
#360
0!
b0 :
1'
#365
0'
#370
b1 7
b10011110001101110111100110111001 ?
b10011110001101110111100110111001 =
b10011110001101110111100110111001 6
1"
b0 >
b0 <
b0 #
b0 ,
b0 8
b0 ;
1'
#375
0'
#380
b10 7
b1 :
1'
#385
0'
#390
0"
b10 :
1'
#395
0'
#400
b11011011010101111100011100101111 ?
b11011011010101111100011100101111 =
b111100011011101111001101110010 6
b1 9
b10011110001101110111100110111001 >
b10011110001101110111100110111001 <
b10011110001101110111100110111001 ;
1'
#405
0'
#410
b11100001101100001011111111000010 ?
b11100001101100001011111111000010 =
b11011010101001100110110100101011 6
b10 9
b11011011010101111100011100101111 >
b11011011010101111100011100101111 <
b111100011011101111001101110010 ;
1'
#415
0'
#420
b101000001110011001111100111010 ?
b101000001110011001111100111010 =
b1111000110111011110011011100100 6
b11 9
b11100001101100001011111111000010 >
b11100001101100001011111111000010 <
b11011010101001100110110100101011 ;
1'
#425
0'
#430
b11100101110100000101111111001000 ?
b11100101110100000101111111001000 =
b10111000101010110000010011101 6
b100 9
b101000001110011001111100111010 >
b101000001110011001111100111010 <
b1111000110111011110011011100100 ;
1'
#435
0'
#440
b10100111000001101010010000101000 ?
b10100111000001101010010000101000 =
b10110101010011001101101001010110 6
b101 9
b11100101110100000101111111001000 >
b11100101110100000101111111001000 <
b10111000101010110000010011101 ;
1'
#445
0'
#450
b110110110111110011001110111110 ?
b110110110111110011001110111110 =
b1010011100001000101010000001111 6
b110 9
b10100111000001101010010000101000 >
b10100111000001101010010000101000 <
b10110101010011001101101001010110 ;
1'
#455
0'
#460
b1111011101111011111011110111001 ?
b1111011101111011111011110111001 =
b11110001101110111100110111001000 6
b111 9
b110110110111110011001110111110 >
b110110110111110011001110111110 <
b1010011100001000101010000001111 ;
1'
#465
0'
#470
b101111011100011010001011010000 ?
b101111011100011010001011010000 =
b10001111111100110100011110000001 6
b1000 9
b1111011101111011111011110111001 >
b1111011101111011111011110111001 <
b11110001101110111100110111001000 ;
1'
#475
0'
#480
b11011011011011110110011011101100 ?
b11011011011011110110011011101100 =
b101110001010101100000100111010 6
b1001 9
b101111011100011010001011010000 >
b101111011100011010001011010000 <
b10001111111100110100011110000001 ;
1'
#485
0'
#490
b11110011011011000001101100010100 ?
b11110011011011000001101100010100 =
b11001100011000100011101011110011 6
b1010 9
b11011011011011110110011011101100 >
b11011011011011110110011011101100 <
b101110001010101100000100111010 ;
1'
#495
0'
#500
b1100010110010110011100101101100 ?
b1100010110010110011100101101100 =
b1101010100110011011010010101100 6
b1011 9
b11110011011011000001101100010100 >
b11110011011011000001101100010100 <
b11001100011000100011101011110011 ;
1'
#505
0'
#510
b10100111000001001110001001000110 ?
b10100111000001001110001001000110 =
b1000110100010010111001100101 6
b1100 9
b1100010110010110011100101101100 >
b1100010110010110011100101101100 <
b1101010100110011011010010101100 ;
1'
#515
0'
#520
b11100010100000000110101101011100 ?
b11100010100000000110101101011100 =
b10100111000010001010100000011110 6
b1101 9
b10100111000001001110001001000110 >
b10100111000001001110001001000110 <
b1000110100010010111001100101 ;
1'
#525
0'
#530
b11101011010100101010011100000101 ?
b11101011010100101010011100000101 =
b1000101010000000010000111010111 6
b1110 9
b11100010100000000110101101011100 >
b11100010100000000110101101011100 <
b10100111000010001010100000011110 ;
1'
#535
0'
#540
b1101000000011010100111100000010 ?
b1101000000011010100111100000010 =
b11100011011101111001101110010000 6
b1111 9
b11101011010100101010011100000101 >
b11101011010100101010011100000101 <
b1000101010000000010000111010111 ;
1'
#545
0'
#550
b11010010001101100100110100010101 ?
b11010010001101100100110100010101 =
b10000001101011110001010101001001 6
b10000 9
b1101000000011010100111100000010 >
b1101000000011010100111100000010 <
b11100011011101111001101110010000 ;
1'
#555
0'
#560
b10101010001000000000110001000100 ?
b10101010001000000000110001000100 =
b11111111001101000111100000010 6
b10001 9
b11010010001101100100110100010101 >
b11010010001101100100110100010101 <
b10000001101011110001010101001001 ;
1'
#565
0'
#570
b1111001100011111101110100100001 ?
b1111001100011111101110100100001 =
b10111110000111100000100010111011 6
b10010 9
b10101010001000000000110001000100 >
b10101010001000000000110001000100 <
b11111111001101000111100000010 ;
1'
#575
0'
#580
b11001000011001001101000010001101 ?
b11001000011001001101000010001101 =
b1011100010101011000001001110100 6
b10011 9
b1111001100011111101110100100001 >
b1111001100011111101110100100001 <
b10111110000111100000100010111011 ;
1'
#585
0'
#590
b1011011001001011001101111011 ?
b1011011001001011001101111011 =
b11111010100011001111110000101101 6
b10100 9
b11001000011001001101000010001101 >
b11001000011001001101000010001101 <
b1011100010101011000001001110100 ;
1'
#595
0'
#600
b11101100111011110111011000101 ?
b11101100111011110111011000101 =
b10011000110001000111010111100110 6
b10101 9
b1011011001001011001101111011 >
b1011011001001011001101111011 <
b11111010100011001111110000101101 ;
1'
#605
0'
#610
b10101011010010011100110000000111 ?
b10101011010010011100110000000111 =
b110110111110111110111110011111 6
b10110 9
b11101100111011110111011000101 >
b11101100111011110111011000101 <
b10011000110001000111010111100110 ;
1'
#615
0'
#620
b11011101000001011000011101010110 ?
b11011101000001011000011101010110 =
b11010101001100110110100101011000 6
b10111 9
b10101011010010011100110000000111 >
b10101011010010011100110000000111 <
b110110111110111110111110011111 ;
1'
#625
0'
#630
b1100011110001011011101010010011 ?
b1100011110001011011101010010011 =
b1110011011010101110001100010001 6
b11000 9
b11011101000001011000011101010110 >
b11011101000001011000011101010110 <
b11010101001100110110100101011000 ;
1'
#635
0'
#640
b10101101111100110100111001001100 ?
b10101101111100110100111001001100 =
b10001101000100101110011001010 6
b11001 9
b1100011110001011011101010010011 >
b1100011110001011011101010010011 <
b1110011011010101110001100010001 ;
1'
#645
0'
#650
b110101100010011010100011001001 ?
b110101100010011010100011001001 =
b10101111110110011101011010000011 6
b11010 9
b10101101111100110100111001001100 >
b10101101111100110100111001001100 <
b10001101000100101110011001010 ;
1'
#655
0'
#660
b10000001101011110000110011100 ?
b10000001101011110000110011100 =
b1001110000100010101000000111100 6
b11011 9
b110101100010011010100011001001 >
b110101100010011010100011001001 <
b10101111110110011101011010000011 ;
1'
#665
0'
#670
b1111110101101111111011111001 ?
b1111110101101111111011111001 =
b11101100010010001100100111110101 6
b11100 9
b10000001101011110000110011100 >
b10000001101011110000110011100 <
b1001110000100010101000000111100 ;
1'
#675
0'
#680
b1110111000111010001100110111001 ?
b1110111000111010001100110111001 =
b10001010100000000100001110101110 6
b11101 9
b1111110101101111111011111001 >
b1111110101101111111011111001 <
b11101100010010001100100111110101 ;
1'
#685
0'
#690
b1100100110110101011111000110110 ?
b1100100110110101011111000110110 =
b101000101101111011110101100111 6
b11110 9
b1110111000111010001100110111001 >
b1110111000111010001100110111001 <
b10001010100000000100001110101110 ;
1'
#695
0'
#700
b11 7
b11001010000111111000000111111101 ?
b11001010000111111000000111111101 =
b11000110111011110011011100100000 6
b11111 9
b1100100110110101011111000110110 >
b1100100110110101011111000110110 <
b101000101101111011110101100111 ;
1'
#705
0'
#710
b1010011000011100101001100000110 ?
b1010011000011100101001100000110 =
b1100101001001101011000011011001 6
b0 9
b11001010000111111000000111111101 >
b11001010000111111000000111111101 <
b11000110111011110011011100100000 ;
b11 :
1'
#715
0'
#720
b0 7
1!
b1100101000011111100000011111110111001010000111111000000111111101 #
b1100101000011111100000011111110111001010000111111000000111111101 ,
b1100101000011111100000011111110111001010000111111000000111111101 8
1'
#725
0'
#730
0!
b0 :
1'
#735
0'
#740
b1 7
b10011110001101110111100110111001 ?
b10011110001101110111100110111001 =
b10011110001101110111100110111001 6
1"
b0 >
b0 <
b0 #
b0 ,
b0 8
b0 ;
1'
#745
0'
#750
b10 7
b1 :
1'
#755
0'
#760
0"
b10 :
1'
#765
0'
#770
b11011011010101111100011100101111 ?
b11011011010101111100011100101111 =
b111100011011101111001101110010 6
b1 9
b10011110001101110111100110111001 >
b10011110001101110111100110111001 <
b10011110001101110111100110111001 ;
1'
#775
0'
#780
b11100001101100001011111111000010 ?
b11100001101100001011111111000010 =
b11011010101001100110110100101011 6
b10 9
b11011011010101111100011100101111 >
b11011011010101111100011100101111 <
b111100011011101111001101110010 ;
1'
#785
0'
#790
b101000001110011001111100111010 ?
b101000001110011001111100111010 =
b1111000110111011110011011100100 6
b11 9
b11100001101100001011111111000010 >
b11100001101100001011111111000010 <
b11011010101001100110110100101011 ;
1'
#795
0'
#800
b11100101110100000101111111001000 ?
b11100101110100000101111111001000 =
b10111000101010110000010011101 6
b100 9
b101000001110011001111100111010 >
b101000001110011001111100111010 <
b1111000110111011110011011100100 ;
1'
#805
0'
#810
b10100111000001101010010000101000 ?
b10100111000001101010010000101000 =
b10110101010011001101101001010110 6
b101 9
b11100101110100000101111111001000 >
b11100101110100000101111111001000 <
b10111000101010110000010011101 ;
1'
#815
0'
#820
b110110110111110011001110111110 ?
b110110110111110011001110111110 =
b1010011100001000101010000001111 6
b110 9
b10100111000001101010010000101000 >
b10100111000001101010010000101000 <
b10110101010011001101101001010110 ;
1'
#825
0'
#830
b1111011101111011111011110111001 ?
b1111011101111011111011110111001 =
b11110001101110111100110111001000 6
b111 9
b110110110111110011001110111110 >
b110110110111110011001110111110 <
b1010011100001000101010000001111 ;
1'
#835
0'
#840
b101111011100011010001011010000 ?
b101111011100011010001011010000 =
b10001111111100110100011110000001 6
b1000 9
b1111011101111011111011110111001 >
b1111011101111011111011110111001 <
b11110001101110111100110111001000 ;
1'
#845
0'
#850
b11011011011011110110011011101100 ?
b11011011011011110110011011101100 =
b101110001010101100000100111010 6
b1001 9
b101111011100011010001011010000 >
b101111011100011010001011010000 <
b10001111111100110100011110000001 ;
1'
#855
0'
#860
b11110011011011000001101100010100 ?
b11110011011011000001101100010100 =
b11001100011000100011101011110011 6
b1010 9
b11011011011011110110011011101100 >
b11011011011011110110011011101100 <
b101110001010101100000100111010 ;
1'
#865
0'
#870
b1100010110010110011100101101100 ?
b1100010110010110011100101101100 =
b1101010100110011011010010101100 6
b1011 9
b11110011011011000001101100010100 >
b11110011011011000001101100010100 <
b11001100011000100011101011110011 ;
1'
#875
0'
#880
b10100111000001001110001001000110 ?
b10100111000001001110001001000110 =
b1000110100010010111001100101 6
b1100 9
b1100010110010110011100101101100 >
b1100010110010110011100101101100 <
b1101010100110011011010010101100 ;
1'
#885
0'
#890
b11100010100000000110101101011100 ?
b11100010100000000110101101011100 =
b10100111000010001010100000011110 6
b1101 9
b10100111000001001110001001000110 >
b10100111000001001110001001000110 <
b1000110100010010111001100101 ;
1'
#895
0'
#900
b11101011010100101010011100000101 ?
b11101011010100101010011100000101 =
b1000101010000000010000111010111 6
b1110 9
b11100010100000000110101101011100 >
b11100010100000000110101101011100 <
b10100111000010001010100000011110 ;
1'
#905
0'
#910
b1101000000011010100111100000010 ?
b1101000000011010100111100000010 =
b11100011011101111001101110010000 6
b1111 9
b11101011010100101010011100000101 >
b11101011010100101010011100000101 <
b1000101010000000010000111010111 ;
1'
#915
0'
#920
b11010010001101100100110100010101 ?
b11010010001101100100110100010101 =
b10000001101011110001010101001001 6
b10000 9
b1101000000011010100111100000010 >
b1101000000011010100111100000010 <
b11100011011101111001101110010000 ;
1'
#925
0'
#930
b10101010001000000000110001000100 ?
b10101010001000000000110001000100 =
b11111111001101000111100000010 6
b10001 9
b11010010001101100100110100010101 >
b11010010001101100100110100010101 <
b10000001101011110001010101001001 ;
1'
#935
0'
#940
b1111001100011111101110100100001 ?
b1111001100011111101110100100001 =
b10111110000111100000100010111011 6
b10010 9
b10101010001000000000110001000100 >
b10101010001000000000110001000100 <
b11111111001101000111100000010 ;
1'
#945
0'
#950
b11001000011001001101000010001101 ?
b11001000011001001101000010001101 =
b1011100010101011000001001110100 6
b10011 9
b1111001100011111101110100100001 >
b1111001100011111101110100100001 <
b10111110000111100000100010111011 ;
1'
#955
0'
#960
b1011011001001011001101111011 ?
b1011011001001011001101111011 =
b11111010100011001111110000101101 6
b10100 9
b11001000011001001101000010001101 >
b11001000011001001101000010001101 <
b1011100010101011000001001110100 ;
1'
#965
0'
#970
b11101100111011110111011000101 ?
b11101100111011110111011000101 =
b10011000110001000111010111100110 6
b10101 9
b1011011001001011001101111011 >
b1011011001001011001101111011 <
b11111010100011001111110000101101 ;
1'
#975
0'
#980
b10101011010010011100110000000111 ?
b10101011010010011100110000000111 =
b110110111110111110111110011111 6
b10110 9
b11101100111011110111011000101 >
b11101100111011110111011000101 <
b10011000110001000111010111100110 ;
1'
#985
0'
#990
b11011101000001011000011101010110 ?
b11011101000001011000011101010110 =
b11010101001100110110100101011000 6
b10111 9
b10101011010010011100110000000111 >
b10101011010010011100110000000111 <
b110110111110111110111110011111 ;
1'
#995
0'
#1000
b1100011110001011011101010010011 ?
b1100011110001011011101010010011 =
b1110011011010101110001100010001 6
b11000 9
b11011101000001011000011101010110 >
b11011101000001011000011101010110 <
b11010101001100110110100101011000 ;
1'
#1005
0'
#1010
b10101101111100110100111001001100 ?
b10101101111100110100111001001100 =
b10001101000100101110011001010 6
b11001 9
b1100011110001011011101010010011 >
b1100011110001011011101010010011 <
b1110011011010101110001100010001 ;
1'
#1015
0'
#1020
b110101100010011010100011001001 ?
b110101100010011010100011001001 =
b10101111110110011101011010000011 6
b11010 9
b10101101111100110100111001001100 >
b10101101111100110100111001001100 <
b10001101000100101110011001010 ;
1'
#1025
0'
#1030
b10000001101011110000110011100 ?
b10000001101011110000110011100 =
b1001110000100010101000000111100 6
b11011 9
b110101100010011010100011001001 >
b110101100010011010100011001001 <
b10101111110110011101011010000011 ;
1'
#1035
0'
#1040
b1111110101101111111011111001 ?
b1111110101101111111011111001 =
b11101100010010001100100111110101 6
b11100 9
b10000001101011110000110011100 >
b10000001101011110000110011100 <
b1001110000100010101000000111100 ;
1'
#1045
0'
#1050
b1110111000111010001100110111001 ?
b1110111000111010001100110111001 =
b10001010100000000100001110101110 6
b11101 9
b1111110101101111111011111001 >
b1111110101101111111011111001 <
b11101100010010001100100111110101 ;
1'
#1055
0'
#1060
b1100100110110101011111000110110 ?
b1100100110110101011111000110110 =
b101000101101111011110101100111 6
b11110 9
b1110111000111010001100110111001 >
b1110111000111010001100110111001 <
b10001010100000000100001110101110 ;
1'
#1065
0'
#1070
b11 7
b11001010000111111000000111111101 ?
b11001010000111111000000111111101 =
b11000110111011110011011100100000 6
b11111 9
b1100100110110101011111000110110 >
b1100100110110101011111000110110 <
b101000101101111011110101100111 ;
1'
#1075
0'
